artvee_scraper_cli/__init__.py
artvee_scraper_cli/runner.py
artvee_scraper_cli/utils.py
artvee_scraper_cli/cli/__init__.py
artvee_scraper_cli/cli/arg_group.py
artvee_scraper_cli/cli/file_arg_group.py
artvee_scraper_cli/cli/log_arg_group.py
artvee_scraper_cli/writer/__init__.py
artvee_scraper_cli/writer/abstract_writer.py
artvee_scraper_cli/writer/command.py
artvee_scraper_cli/writer/file_writer.py
artvee_scraper_cli/writer/log_writer.py
artvee_scraper_cli/writer/writer_factory.py
artvee_scraper_cli-1.0.1.dist-info/LICENSE
artvee_scraper_cli-1.0.1.dist-info/METADATA
artvee_scraper_cli-1.0.1.dist-info/WHEEL
artvee_scraper_cli-1.0.1.dist-info/entry_points.txt
artvee_scraper_cli-1.0.1.dist-info/top_level.txt
artvee_scraper_cli-1.0.1.dist-info/zip-safe
artvee_scraper_cli-1.0.1.dist-info/RECORD
