Metadata-Version: 2.1
Name: artvee-scraper-cli
Version: 1.0.1
Summary: Fetch public domain artwork from Artvee
Home-page: https://github.com/zduclos/artvee-scraper-cli
Author: Zach Duclos
Author-email: zduclos.github@gmail.com
License: MIT
Project-URL: Bug Reports, https://github.com/zduclos/artvee-scraper-cli/issues
Project-URL: Source, https://github.com/zduclos/artvee-scraper-cli
Keywords: artvee,artwork,webscraper
Classifier: Development Status :: 5 - Production/Stable
Classifier: Intended Audience :: Developers
Classifier: Natural Language :: English
Classifier: Environment :: Console
Classifier: License :: OSI Approved :: MIT License
Classifier: Programming Language :: Python
Classifier: Programming Language :: Python :: 3
Classifier: Programming Language :: Python :: 3.10
Classifier: Programming Language :: Python :: 3.11
Classifier: Programming Language :: Python :: 3.12
Classifier: Operating System :: OS Independent
Requires-Python: >= 3.10
License-File: LICENSE
Requires-Dist: artvee-scraper (~=4.0.4)
